{
	"info": {
		"_postman_id": "23218e1a-062a-4349-8857-a42c21617ecf",
		"name": "2901-group",
		"schema": "https://schema.getpostman.com/json/collection/v2.1.0/collection.json"
	},
	"item": [
		{
			"name": "CRUD.pet",
			"item": [
				{
					"name": "CREATE",
					"event": [
						{
							"listen": "prerequest",
							"script": {
								"exec": [
									"pm.environment.set(\"pet_id\", _.random(1,50000));"
								],
								"type": "text/javascript"
							}
						},
						{
							"listen": "test",
							"script": {
								"exec": [
									"pm.test(\"Status code is 200\", function () {\r",
									"    pm.response.to.have.status(200);\r",
									"});\r",
									"\r",
									"\r",
									"var jsonData = pm.response.json();\r",
									"pm.test(\"Response ID the same as in environment\", function () {\r",
									"    pm.expect(jsonData.id).to.eql(pm.environment.get(\"pet_id\"));\r",
									"});"
								],
								"type": "text/javascript"
							}
						}
					],
					"request": {
						"method": "POST",
						"header": [],
						"body": {
							"mode": "raw",
							"raw": "{\r\n  \"id\": {{pet_id}},\r\n  \"category\": {\r\n    \"id\": 321,\r\n    \"name\": \"ASD-category\"\r\n  },\r\n  \"name\": \"doggie\",\r\n  \"photoUrls\": [\r\n    \"syyyg\"\r\n  ],\r\n  \"tags\": [\r\n    {\r\n      \"id\": 654,\r\n      \"name\": \"ereryrtt\"\r\n    }\r\n  ],\r\n  \"status\": \"available\"\r\n}",
							"options": {
								"raw": {
									"language": "json"
								}
							}
						},
						"url": {
							"raw": "https://petstore.swagger.io/v2/pet",
							"protocol": "https",
							"host": [
								"petstore",
								"swagger",
								"io"
							],
							"path": [
								"v2",
								"pet"
							]
						}
					},
					"response": []
				},
				{
					"name": "READ",
					"event": [
						{
							"listen": "test",
							"script": {
								"exec": [
									"pm.test(\"Status code is 200\", function () {\r",
									"    pm.response.to.have.status(200);\r",
									"});\r",
									"var jsonData = pm.response.json();\r",
									"pm.test(\"Response ID the same as in environment\", function () {\r",
									"    pm.expect(jsonData.id).to.eql(pm.environment.get(\"pet_id\"));\r",
									"});"
								],
								"type": "text/javascript"
							}
						},
						{
							"listen": "prerequest",
							"script": {
								"exec": [
									""
								],
								"type": "text/javascript"
							}
						}
					],
					"protocolProfileBehavior": {
						"disableBodyPruning": true
					},
					"request": {
						"method": "GET",
						"header": [],
						"body": {
							"mode": "raw",
							"raw": ""
						},
						"url": {
							"raw": "https://petstore.swagger.io/v2/pet/{{pet_id}}",
							"protocol": "https",
							"host": [
								"petstore",
								"swagger",
								"io"
							],
							"path": [
								"v2",
								"pet",
								"{{pet_id}}"
							]
						}
					},
					"response": []
				},
				{
					"name": "UPDATE",
					"event": [
						{
							"listen": "prerequest",
							"script": {
								"exec": [
									"pm.environment.set(\"pet_id\", _.random(1,50000));"
								],
								"type": "text/javascript"
							}
						},
						{
							"listen": "test",
							"script": {
								"exec": [
									"pm.test(\"Status code is 200\", function () {\r",
									"    pm.response.to.have.status(200);\r",
									"});\r",
									"\r",
									"\r",
									"var jsonData = pm.response.json();\r",
									"pm.test(\"Response ID the same as in environment\", function () {\r",
									"    pm.expect(jsonData.id).to.eql(pm.environment.get(\"pet_id\"));\r",
									"});"
								],
								"type": "text/javascript"
							}
						}
					],
					"request": {
						"method": "PUT",
						"header": [],
						"body": {
							"mode": "raw",
							"raw": "{\r\n  \"id\":{{pet_id}},\r\n  \"category\": {\r\n    \"id\": 321,\r\n    \"name\": \"ASD-category\"\r\n  },\r\n  \"name\": \"doggie\",\r\n  \"photoUrls\": [\r\n    \"ssssssssssssssssssssssssssss\"\r\n  ],\r\n  \"tags\": [\r\n    {\r\n      \"id\": 654,\r\n      \"name\": \"ereryrtt\"\r\n    }\r\n  ],\r\n  \"status\": \"available\"\r\n}",
							"options": {
								"raw": {
									"language": "json"
								}
							}
						},
						"url": {
							"raw": "https://petstore.swagger.io/v2/pet",
							"protocol": "https",
							"host": [
								"petstore",
								"swagger",
								"io"
							],
							"path": [
								"v2",
								"pet"
							]
						}
					},
					"response": []
				},
				{
					"name": "READ",
					"event": [
						{
							"listen": "prerequest",
							"script": {
								"exec": [
									""
								],
								"type": "text/javascript"
							}
						},
						{
							"listen": "test",
							"script": {
								"exec": [
									"pm.test(\"Status code is 200\", function () {\r",
									"    pm.response.to.have.status(200);\r",
									"});\r",
									"var jsonData = pm.response.json();\r",
									"pm.test(\"Response ID the same as in environment\", function () {\r",
									"    pm.expect(jsonData.id).to.eql(pm.environment.get(\"pet_id\"));\r",
									"});"
								],
								"type": "text/javascript"
							}
						}
					],
					"protocolProfileBehavior": {
						"disableBodyPruning": true
					},
					"request": {
						"method": "GET",
						"header": [],
						"body": {
							"mode": "raw",
							"raw": "",
							"options": {
								"raw": {
									"language": "json"
								}
							}
						},
						"url": {
							"raw": "https://petstore.swagger.io/v2/pet/{{pet_id}}",
							"protocol": "https",
							"host": [
								"petstore",
								"swagger",
								"io"
							],
							"path": [
								"v2",
								"pet",
								"{{pet_id}}"
							]
						}
					},
					"response": []
				},
				{
					"name": "DELETE",
					"event": [
						{
							"listen": "prerequest",
							"script": {
								"exec": [
									""
								],
								"type": "text/javascript"
							}
						},
						{
							"listen": "test",
							"script": {
								"exec": [
									"pm.test(\"Status code is 200\", function () {\r",
									"    pm.response.to.have.status(200);\r",
									"});\r",
									"\r",
									""
								],
								"type": "text/javascript"
							}
						}
					],
					"request": {
						"method": "DELETE",
						"header": [],
						"body": {
							"mode": "raw",
							"raw": "",
							"options": {
								"raw": {
									"language": "json"
								}
							}
						},
						"url": {
							"raw": "https://petstore.swagger.io/v2/pet/{{pet_id}}",
							"protocol": "https",
							"host": [
								"petstore",
								"swagger",
								"io"
							],
							"path": [
								"v2",
								"pet",
								"{{pet_id}}"
							]
						}
					},
					"response": []
				},
				{
					"name": "READ",
					"event": [
						{
							"listen": "test",
							"script": {
								"exec": [
									"pm.test(\"Status code is 200\", function () {\r",
									"    pm.response.to.have.status(200);\r",
									"});\r",
									""
								],
								"type": "text/javascript"
							}
						}
					],
					"request": {
						"method": "GET",
						"header": [],
						"url": {
							"raw": "https://petstore.swagger.io/v2/pet/{{pet_id}}",
							"protocol": "https",
							"host": [
								"petstore",
								"swagger",
								"io"
							],
							"path": [
								"v2",
								"pet",
								"{{pet_id}}"
							]
						}
					},
					"response": []
				}
			]
		},
		{
			"name": "get vkcom",
			"event": [
				{
					"listen": "test",
					"script": {
						"exec": [
							"pm.test(\"Status code is 200\", function () {\r",
							"    pm.response.to.have.status(200);\r",
							"});\r",
							"pm.test(\"Response time is less than 2000ms\", function () {\r",
							"    pm.expect(pm.response.responseTime).to.be.below(2000);\r",
							"});"
						],
						"type": "text/javascript"
					}
				}
			],
			"request": {
				"auth": {
					"type": "noauth"
				},
				"method": "GET",
				"header": [],
				"url": {
					"raw": "vk.com",
					"host": [
						"vk",
						"com"
					]
				}
			},
			"response": []
		}
	]
}